EvoCluster/__init__.py
EvoCluster/_cluster_detection.py
EvoCluster/_evocluster.py
EvoCluster/_measures.py
EvoCluster/_objectives.py
EvoCluster/_plot_boxplot.py
EvoCluster/_plot_convergence.py
EvoCluster/_solution.py
EvoCluster/cli.py
EvoCluster/datasets/Blood.csv
EvoCluster/datasets/XXX.csv
EvoCluster/datasets/aggregation.csv
EvoCluster/datasets/aniso.csv
EvoCluster/datasets/appendicitis.csv
EvoCluster/datasets/balance.csv
EvoCluster/datasets/banknote.csv
EvoCluster/datasets/blobs.csv
EvoCluster/datasets/circles.csv
EvoCluster/datasets/diagnosis_II.csv
EvoCluster/datasets/ecoli.csv
EvoCluster/datasets/flame.csv
EvoCluster/datasets/glass.csv
EvoCluster/datasets/heart.csv
EvoCluster/datasets/ionosphere.csv
EvoCluster/datasets/iris.csv
EvoCluster/datasets/iris2D.csv
EvoCluster/datasets/jain.csv
EvoCluster/datasets/liver.csv
EvoCluster/datasets/moons.csv
EvoCluster/datasets/mouse.csv
EvoCluster/datasets/pathbased.csv
EvoCluster/datasets/seeds.csv
EvoCluster/datasets/smiley.csv
EvoCluster/datasets/sonar.csv
EvoCluster/datasets/test.csv
EvoCluster/datasets/train.csv
EvoCluster/datasets/varied.csv
EvoCluster/datasets/vary-density.csv
EvoCluster/datasets/vertebral2.csv
EvoCluster/datasets/vertebral3.csv
EvoCluster/datasets/wdbc.csv
EvoCluster/datasets/wine.csv
EvoCluster/optimizers/CBAT.py
EvoCluster/optimizers/CCS.py
EvoCluster/optimizers/CFFA.py
EvoCluster/optimizers/CGA.py
EvoCluster/optimizers/CGWO.py
EvoCluster/optimizers/CMFO.py
EvoCluster/optimizers/CMVO.py
EvoCluster/optimizers/CPSO.py
EvoCluster/optimizers/CSSA.py
EvoCluster/optimizers/CWOA.py
EvoCluster/optimizers/__init__.py
tests/__init__.py
tests/test_cli.py
EvoCluster-1.0.6.dist-info/LICENSE
EvoCluster-1.0.6.dist-info/METADATA
EvoCluster-1.0.6.dist-info/WHEEL
EvoCluster-1.0.6.dist-info/top_level.txt
EvoCluster-1.0.6.dist-info/RECORD
