Metadata-Version: 2.1
Name: EvoCluster
Version: 1.0.6
Summary: An Open-Source Nature-Inspired Optimization Clustering Framework in Python
Home-page: https://github.com/RaneemQaddoura/EvoCluster
Author: Raneem Qaddoura, Hossam Faris, Ibrahim Aljarah, and Pedro A. Castillo
Author-email: dangtrunganh@gmail.com, raneem.qaddoura@gmail.com
License: UNKNOWN
Keywords: python,first package
Platform: UNKNOWN
Classifier: Development Status :: 3 - Alpha
Classifier: Intended Audience :: Education
Classifier: Programming Language :: Python :: 2
Classifier: Programming Language :: Python :: 3
Classifier: Operating System :: MacOS :: MacOS X
Classifier: Operating System :: Microsoft :: Windows
License-File: LICENSE
Requires-Dist: NumPy
Requires-Dist: SciPy
Requires-Dist: sklearn
Requires-Dist: pandas
Requires-Dist: matplotlib
